ccepy/__init__.py
ccepy/aritmetica_elemental.py
ccepy/cuerpos_finitos.py
ccepy/curvas_elipticas.py
ccepy/esquemas_criptograficos.py
ccepy/listado_curvas_elipticas.py
ccepy-1.0.1.dist-info/DESCRIPTION.rst
ccepy-1.0.1.dist-info/METADATA
ccepy-1.0.1.dist-info/RECORD
ccepy-1.0.1.dist-info/WHEEL
ccepy-1.0.1.dist-info/entry_points.txt
ccepy-1.0.1.dist-info/metadata.json
ccepy-1.0.1.dist-info/top_level.txt
