Metadata-Version: 2.0
Name: ccepy
Version: 1.0.1
Summary: Criptografía con Curvas Elípticas con Python
Home-page: https://github.com/ranea/ccepy
Author: Adrian Ranea
Author-email: adrianranea@gmail.com
License: MIT
Keywords: criptografía curvas elípticas llave pública protocolos criptográficos
Platform: UNKNOWN
Classifier: Development Status :: 5 - Production/Stable
Classifier: Intended Audience :: Science/Research
Classifier: Topic :: Security :: Cryptography
Classifier: License :: OSI Approved :: MIT License
Classifier: Programming Language :: Python :: 3
Classifier: Programming Language :: Python :: 3.3
Classifier: Programming Language :: Python :: 3.4
Classifier: Programming Language :: Python :: 3.5
Provides-Extra: dev
Requires-Dist: sphinx; extra == 'dev'
Provides-Extra: test
Requires-Dist: hypothesis; extra == 'test'
